netbox_plugin_gpon/__init__.py
netbox_plugin_gpon/admin.py
netbox_plugin_gpon/filters.py
netbox_plugin_gpon/forms.py
netbox_plugin_gpon/migrations/0001_initial.py
netbox_plugin_gpon/migrations/0002_ispactivedevice_ispdevice_olt.py
netbox_plugin_gpon/migrations/0003_auto_20210726_0202.py
netbox_plugin_gpon/migrations/0004_ont.py
netbox_plugin_gpon/migrations/0005_alter_ispdevice_uuid.py
netbox_plugin_gpon/migrations/0006_remove_ispdevice_uuid.py
netbox_plugin_gpon/migrations/__init__.py
netbox_plugin_gpon/models.py
netbox_plugin_gpon/navigation.py
netbox_plugin_gpon/netbox_plugin_gpon/__init__.py
netbox_plugin_gpon/netbox_plugin_gpon/utilities/__init__.py
netbox_plugin_gpon/netbox_plugin_gpon/utilities/tables.py
netbox_plugin_gpon/netbox_plugin_gpon/views/__init__.py
netbox_plugin_gpon/netbox_plugin_gpon/views/generic.py
netbox_plugin_gpon/pyproject.toml
netbox_plugin_gpon/tables.py
netbox_plugin_gpon/templates/__init__.py
netbox_plugin_gpon/templates/netbox_plugin_gpon/__init__.py
netbox_plugin_gpon/templates/netbox_plugin_gpon/generic/__init__.py
netbox_plugin_gpon/templates/netbox_plugin_gpon/generic/object_edit.html
netbox_plugin_gpon/templates/netbox_plugin_gpon/generic/object_list.html
netbox_plugin_gpon/templates/netbox_plugin_gpon/home.html
netbox_plugin_gpon/templates/netbox_plugin_gpon/olt.html
netbox_plugin_gpon/templates/netbox_plugin_gpon/onu.html
netbox_plugin_gpon/templatetags/__init__.py
netbox_plugin_gpon/templatetags/plugin_extras.py
netbox_plugin_gpon/urls.py
netbox_plugin_gpon/views.py
netbox_plugin_gpon-1.0.0.dist-info/WHEEL
netbox_plugin_gpon-1.0.0.dist-info/METADATA
netbox_plugin_gpon-1.0.0.dist-info/RECORD
