Metadata-Version: 2.1
Name: netbox-plugin-gpon
Version: 1.0.0
Summary: This package adds GPON OLTs, ONTs, and Splitter logic and database operations to Netbox.
Home-page: https://github.com/MajesticFalcon/netbox_plugin_gpon
Author: sutley
Requires-Python: >=3.6,<4.0
Classifier: Programming Language :: Python :: 3
Classifier: Programming Language :: Python :: 3.6
Classifier: Programming Language :: Python :: 3.7
Classifier: Programming Language :: Python :: 3.8
Classifier: Programming Language :: Python :: 3.9
Project-URL: Repository, https://github.com/MajesticFalcon/netbox_plugin_gpon
